ablation/__init__.py
ablation/ablation.py
ablation/baseline.py
ablation/dataset.py
ablation/distributions.py
ablation/experiment.py
ablation/explanations.py
ablation/perturb.py
ablation/pytorch_explanations.py
ablation/pytorch_model.py
ablation/data/MyGermanData.csv
ablation/data/adult.data
ablation/data/adult.test
ablation/data/download.sh
ablation/data/har_features.txt
ablation/data/har_x_test.pkl
ablation/data/har_x_train.pkl
ablation/data/har_y_test.pkl
ablation/data/har_y_train.pkl
ablation/data/spambase-X.csv
ablation/data/spambase-y.csv
ablation/utils/__init__.py
ablation/utils/evaluate.py
ablation/utils/logging.py
ablation/utils/model.py
ablation/utils/transform.py
ablation-0.1.0.data/data/ablation/data/MyGermanData.csv
ablation-0.1.0.data/data/ablation/data/adult.data
ablation-0.1.0.data/data/ablation/data/adult.test
ablation-0.1.0.data/data/ablation/data/download.sh
ablation-0.1.0.data/data/ablation/data/har_features.txt
ablation-0.1.0.data/data/ablation/data/har_x_test.pkl
ablation-0.1.0.data/data/ablation/data/har_x_train.pkl
ablation-0.1.0.data/data/ablation/data/har_y_test.pkl
ablation-0.1.0.data/data/ablation/data/har_y_train.pkl
ablation-0.1.0.data/data/ablation/data/spambase-X.csv
ablation-0.1.0.data/data/ablation/data/spambase-y.csv
tests/__init__.py
tests/conftest.py
tests/unittests/test_ablation.py
tests/unittests/test_dataset.py
tests/unittests/test_distribution.py
tests/unittests/test_experiment.py
tests/unittests/test_explanation.py
tests/unittests/test_training.py
tests/unittests/test_transform.py
tests/unittests/test_files/test_config.yml
tests/unittests/test_files/test_config_new.yml
tests/unittests/test_files/test_config_reload.yml
tests/unittests/test_files/test_result.csv
ablation-0.1.0.dist-info/LICENSE
ablation-0.1.0.dist-info/METADATA
ablation-0.1.0.dist-info/WHEEL
ablation-0.1.0.dist-info/top_level.txt
ablation-0.1.0.dist-info/RECORD
